{"county":"Sullivan","countySeat":"Laporte","judicialDistrict":"53rd Judicial District of Pennsylvania","lastUpdated":"2026-02-21","courtInformation":{"courtOfCommonPleas":{"name":"Court of Common Pleas of Sullivan County","address":"245 Muncy Street","city":"Laporte","state":"PA","zip":"18626","phone":"(570) 946-7201"}},"clerkInformation":{"name":"Sullivan County Clerk of Courts","address":"245 Muncy Street","city":"Laporte","state":"PA","zip":"18626","phone":"(570) 946-7201","website":"https://www.sullivancounty.org"},"districtAttorney":{"office":"Sullivan County District Attorney's Office","phone":"(570) 946-7201"},"fees":{"filingFee":0,"expungementFee":0},"cleanSlateStatus":{"localImplementation":"Full Clean Slate implementation"},"notes":["Sullivan County follows Pennsylvania Clean Slate Act"]}
